mkwhl/common.py
mkwhl/__init__.py
mkwhl/wheel.py
mkwhl/build.py
mkwhl/main.py
mkwhl/__main__.py
mkwhl/props.py
mkwhl/dist_info.py
mkwhl-0.3.1.data/data/share/man/man1/mkwhl.1
mkwhl-0.3.1.dist-info/LICENSE
mkwhl-0.3.1.dist-info/entry_points.txt
mkwhl-0.3.1.dist-info/METADATA
mkwhl-0.3.1.dist-info/WHEEL
mkwhl-0.3.1.dist-info/RECORD
