Metadata-Version: 2.1
Name: mkwhl
Version: 0.3.1
Summary: Python wheel creation utility
Author: Bozo Kopic
Author-email: "Bozo Kopic" <bozo@kopic.xyz>
License: GPLv3
Classifier: Programming Language :: Python :: 3
Classifier: License :: OSI Approved :: GNU General Public License v3 (GPLv3)
Requires-Dist: packaging >=23.1
Requires-Dist: tomli ~=2.0.1; python_version<'3.11'
Requires-Python: >=3.10
Project-URL: Repository, https://github.com/bozokopic/mkwhl.git
